portus_unpack/__init__.py
portus_unpack/__main__.py
portus_unpack/parser.py
portus_unpack/portus_unpack.py
portus_unpack/utils.py
portus_unpack/writer.py
portus_unpack/adapters/__init__.py
portus_unpack/adapters/adapter_anthropic.py
portus_unpack/adapters/adapter_chatgpt.py
portus_unpack-1.0.0.dist-info/licenses/LICENSE
portus_unpack-1.0.0.dist-info/METADATA
portus_unpack-1.0.0.dist-info/WHEEL
portus_unpack-1.0.0.dist-info/entry_points.txt
portus_unpack-1.0.0.dist-info/top_level.txt
portus_unpack-1.0.0.dist-info/RECORD
