Metadata-Version: 2.4
Name: portus-unpack
Version: 1.0.0
Summary: Portus-Unpack – CLI to unpack & split ChatGPT / Anthropic exports.
Author: PerceivingAI
License-Expression: MIT
Project-URL: Homepage, https://github.com/PerceivingAI/portus-unpack
Requires-Python: >=3.8
License-File: LICENSE
Requires-Dist: tiktoken
Provides-Extra: progress
Requires-Dist: tqdm>=4.0; extra == "progress"
Dynamic: license-file
